config/__init__.py
config/plate-design.json
data/__init__.py
data/1/02-1055-2013185143-1-14-UKMYC5-raw.png
data/1/output/02-1055-2013185143-1-14-UKMYC5-filtered.png
data/1/output/02-1055-2013185143-1-14-UKMYC5-mics.csv
data/1/output/sampleoutput.png
data/2/01-DR0053-DR0053-1-14-UKMYC6-raw.png
data/3/01-DR0013-DR0013-1-14-UKMYC6-raw.png
data/4/01-DR0053-DR0053-1-14-UKMYC6-raw.png
data/5/10-YA00125818-LA00125818-1-14-UKMYC6-raw.png
scripts/__init__.py
scripts/run_tmas.py
tmas/__init__.py
tmas/docs/Makefile
tmas/docs/OutputImage.png
tmas/docs/api_reference.rst
tmas/docs/changelog.md
tmas/docs/conduct.md
tmas/docs/conf.py
tmas/docs/contributing.md
tmas/docs/example.ipynb
tmas/docs/index.rst
tmas/docs/make.bat
tmas/docs/_build/doctrees/api_reference.doctree
tmas/docs/_build/doctrees/changelog.doctree
tmas/docs/_build/doctrees/conduct.doctree
tmas/docs/_build/doctrees/contributing.doctree
tmas/docs/_build/doctrees/environment.pickle
tmas/docs/_build/doctrees/index.doctree
tmas/docs/_build/doctrees/autoapi/index.doctree
tmas/docs/_build/doctrees/autoapi/conf/index.doctree
tmas/docs/_build/doctrees/autoapi/tmas/index.doctree
tmas/docs/_build/doctrees/autoapi/tmas/src/index.doctree
tmas/docs/_build/doctrees/autoapi/tmas/src/analysis/index.doctree
tmas/docs/_build/doctrees/autoapi/tmas/src/config/index.doctree
tmas/docs/_build/doctrees/autoapi/tmas/src/detection/index.doctree
tmas/docs/_build/doctrees/autoapi/tmas/src/input_validation/index.doctree
tmas/docs/_build/doctrees/autoapi/tmas/src/models/index.doctree
tmas/docs/_build/doctrees/autoapi/tmas/src/models/yolo/index.doctree
tmas/docs/_build/doctrees/autoapi/tmas/src/preprocessing/index.doctree
tmas/docs/_build/doctrees/autoapi/tmas/src/process_image_file/index.doctree
tmas/docs/_build/doctrees/autoapi/tmas/src/utils/index.doctree
tmas/docs/_build/html/.buildinfo
tmas/docs/_build/html/api_reference.html
tmas/docs/_build/html/changelog.html
tmas/docs/_build/html/conduct.html
tmas/docs/_build/html/contributing.html
tmas-1.0.2.dist-info/METADATA
tmas-1.0.2.dist-info/WHEEL
tmas-1.0.2.dist-info/entry_points.txt
tmas-1.0.2.dist-info/top_level.txt
tmas-1.0.2.dist-info/RECORD
