Metadata-Version: 2.1
Name: tmas
Version: 1.0.2
Summary: The package uses deep learning to detect M. tuberculosis growth in 96-well microtiter plates and determines **Minimum Inhibitory Concentrations (MICs)**.
Home-page: https://github.com/Oucru-Innovations/tmas
Author: Hoang-Anh T Vo, Sang Nguyen, Ai-Quynh T Tran, Han Nguyen
Author-email: tmas.2002team@gmail.com
Requires-Python: >=3.9
Requires-Dist: numpy
Requires-Dist: opencv-python
Requires-Dist: torch
Requires-Dist: scikit-learn
Requires-Dist: requests
Requires-Dist: ultralytics
